trialtracker/__init__.py
trialtracker-0.1.7.dist-info/LICENSE
trialtracker-0.1.7.dist-info/METADATA
trialtracker-0.1.7.dist-info/WHEEL
trialtracker-0.1.7.dist-info/top_level.txt
trialtracker-0.1.7.dist-info/RECORD
